<?xml version="1.0" encoding="UTF-8"?>
<QCARConfig xmlns:xsi="http://www.w3.org/2001/XMLSchema-instance" xsi:noNamespaceSchemaLocation="qcar_config.xsd">
  <Tracking>
    <ImageTarget name="GlindaTarget" size="1.000000 0.562075" />
    <ImageTarget name="Passive2Poppies" size="100.000000 133.333328" />
    <ImageTarget name="Passive4GreenGlasses" size="100.000000 133.333328" />
    <ImageTarget name="Passive1Cylone" size="100.000000 133.333328" />
    <ImageTarget name="Passive3Monkey" size="100.000000 133.333328" />
    <ImageTarget name="Oz_TopTarget_inverted" size="4.420000 2.525130" />
  </Tracking>
</QCARConfig>
